archive_utility/__init__.py
archive_utility/app.py
archive_utility/dumper.py
archive_utility/fyle_connection.py
fyle_archive_utility-0.2.1.dist-info/LICENSE
fyle_archive_utility-0.2.1.dist-info/METADATA
fyle_archive_utility-0.2.1.dist-info/WHEEL
fyle_archive_utility-0.2.1.dist-info/entry_points.txt
fyle_archive_utility-0.2.1.dist-info/top_level.txt
fyle_archive_utility-0.2.1.dist-info/RECORD
