Metadata-Version: 2.1
Name: fyle-archive-utility
Version: 0.2.1
Summary: Command-line tool to download Fyle data.
Home-page: https://github.com/fylein/fyle-archive-utility
Author: Fyle
Author-email: sravan.kumar@fyle.in
License: MIT
Keywords: fyle,data,archive,download,csv,json,python,sdk
Platform: UNKNOWN
Classifier: Topic :: Internet :: WWW/HTTP
Classifier: Intended Audience :: Developers
Classifier: Programming Language :: Python :: 3
Classifier: License :: OSI Approved :: MIT License
Classifier: Operating System :: OS Independent
Requires-Dist: logger (==1.4)
Requires-Dist: Click (==7.0)
Requires-Dist: fylesdk (==0.10.0)
